[
  {
    "method": "naive",
    "dataset": "musique",
    "n": 1000,
    "norm_em": 0.053,
    "token_f1": 0.1304,
    "contain": 0.08,
    "mean_tokens": 877.1
  },
  {
    "method": "ircot",
    "dataset": "musique",
    "n": 1000,
    "norm_em": 0.075,
    "token_f1": 0.1283,
    "contain": 0.143,
    "mean_tokens": 7895.7
  },
  {
    "method": "opera",
    "dataset": "musique",
    "n": 1000,
    "norm_em": 0.106,
    "token_f1": 0.1675,
    "contain": 0.168,
    "mean_tokens": 3445.4
  },
  {
    "method": "ma-rag",
    "dataset": "musique",
    "n": 1000,
    "norm_em": 0.124,
    "token_f1": 0.2238,
    "contain": 0.215,
    "mean_tokens": 9667.3
  },
  {
    "method": "naive",
    "dataset": "2wikimultihop",
    "n": 1000,
    "norm_em": 0.209,
    "token_f1": 0.282,
    "contain": 0.295,
    "mean_tokens": 922.0
  },
  {
    "method": "ircot",
    "dataset": "2wikimultihop",
    "n": 1000,
    "norm_em": 0.159,
    "token_f1": 0.2555,
    "contain": 0.559,
    "mean_tokens": 7579.4
  },
  {
    "method": "opera",
    "dataset": "2wikimultihop",
    "n": 1000,
    "norm_em": 0.082,
    "token_f1": 0.1439,
    "contain": 0.193,
    "mean_tokens": 3672.8
  },
  {
    "method": "ma-rag",
    "dataset": "2wikimultihop",
    "n": 1000,
    "norm_em": 0.218,
    "token_f1": 0.3248,
    "contain": 0.473,
    "mean_tokens": 9416.4
  },
  {
    "method": "naive",
    "dataset": "hotpotqa",
    "n": 1000,
    "norm_em": 0.323,
    "token_f1": 0.4434,
    "contain": 0.407,
    "mean_tokens": 885.0
  },
  {
    "method": "ircot",
    "dataset": "hotpotqa",
    "n": 1000,
    "norm_em": 0.311,
    "token_f1": 0.4104,
    "contain": 0.485,
    "mean_tokens": 6456.6
  },
  {
    "method": "opera",
    "dataset": "hotpotqa",
    "n": 1000,
    "norm_em": 0.143,
    "token_f1": 0.2308,
    "contain": 0.293,
    "mean_tokens": 3069.9
  },
  {
    "method": "ma-rag",
    "dataset": "hotpotqa",
    "n": 1000,
    "norm_em": 0.244,
    "token_f1": 0.3642,
    "contain": 0.426,
    "mean_tokens": 8829.5
  },
  {
    "method": "naive",
    "dataset": "bamboogle",
    "n": 125,
    "norm_em": 0.16,
    "token_f1": 0.3091,
    "contain": 0.192,
    "mean_tokens": 854.4
  },
  {
    "method": "ircot",
    "dataset": "bamboogle",
    "n": 125,
    "norm_em": 0.208,
    "token_f1": 0.3109,
    "contain": 0.32,
    "mean_tokens": 6774.5
  },
  {
    "method": "opera",
    "dataset": "bamboogle",
    "n": 125,
    "norm_em": 0.264,
    "token_f1": 0.3819,
    "contain": 0.328,
    "mean_tokens": 2720.4
  },
  {
    "method": "ma-rag",
    "dataset": "bamboogle",
    "n": 125,
    "norm_em": 0.384,
    "token_f1": 0.505,
    "contain": 0.504,
    "mean_tokens": 6827.5
  }
]